{
   
    "lawyers": [
        {
            "name": "ဒေါ် နှင်းဇာဖြူ ထွဏ်း",
            "phone": "09793735979"
        },
        {
            "name": "ဦး မင်းကိုကို",
            "phone": "09425264486"
        },
        {
            "name": "ဦး စိုးလင်းထက်",
            "phone": "09425283843"
        },
        {
            "name": "ဦး ချစ်သဲမောင်",
            "phone": "09789666113"
        },
        {
            "name": "ဦး ဇင်မင်းထက်",
            "phone": "09 455388100"
        },
        {
            "name": "ဒေါ် အေးသက်မွန်",
            "phone": "09425273727"
        },
        {
            "name": "ဒေါ် နှင်းထက်ပိုင်",
            "phone": "09255761864"
        },
        {
            "name": "ဒေါ် ထားထားရီ",
            "phone": "09450339948"
        },
        {
            "name": "ဦး လှိုင်မင်းသက်ထွန်း",
            "phone": "09457470731"
        },
        {
            "name": "ဒေါ် ချမ်းမြေ့ အေး",
            "phone": "09967090636"
        },
        {
            "name": "ဒေါ် ထွဋ်ထွဋ်ဝင်း",
            "phone": "09425345233"
        },
        {
            "name": "ဒေါ် သဇင်စိုး",
            "phone": "09882431494"
        },
        {
            "name": "ဒေါ် နေကြာစိုး",
            "phone": "09255816281"
        },
        {
            "name": "ဒေါ် သင်းအိဖြူ",
            "phone": "09789682174"
        },
        {
            "name": "ဦး နေလင်းထိုက်",
            "phone": "09777264880"
        }
    ]
}
